cherry/__init__.py
cherry/database/__init__.py
cherry/database/engine.py
cherry/exception.py
cherry/fields/__init__.py
cherry/fields/annotated.py
cherry/fields/fields.py
cherry/fields/proxy.py
cherry/fields/types.py
cherry/fields/utils.py
cherry/helpers.py
cherry/meta/__init__.py
cherry/meta/config.py
cherry/meta/index.py
cherry/meta/meta.py
cherry/models/__init__.py
cherry/models/models.py
cherry/queryset/__init__.py
cherry/queryset/protocol.py
cherry/queryset/queryset.py
cherry/typing.py
cherry_orm-1.0.0.dist-info/LICENSE
cherry_orm-1.0.0.dist-info/METADATA
cherry_orm-1.0.0.dist-info/WHEEL
cherry_orm-1.0.0.dist-info/RECORD
