Metadata-Version: 2.1
Name: cherry-orm
Version: 1.0.0
Summary: Python asynchronous ORM based on SQLAlchemy and Pydantic.
License: MIT
Keywords: database,orm,sqlalchemy,pydantic,asyncio
Author: CMHopeSunshine
Author-email: 277073121@qq.com
Requires-Python: >=3.9,<4.0
Classifier: License :: OSI Approved :: MIT License
Classifier: Programming Language :: Python :: 3
Classifier: Programming Language :: Python :: 3.9
Classifier: Programming Language :: Python :: 3.10
Classifier: Programming Language :: Python :: 3.11
Classifier: Programming Language :: Python :: 3.12
Provides-Extra: aiomysql
Provides-Extra: aiosqlite
Provides-Extra: all
Provides-Extra: asyncmy
Provides-Extra: asyncpg
Provides-Extra: mysql
Provides-Extra: postgresql
Provides-Extra: psycopg
Provides-Extra: sqlite
Requires-Dist: SQLAlchemy (>=2.0.22,<3.0.0)
Requires-Dist: aiosqlite (>=0.19.0,<0.20.0) ; extra == "sqlite" or extra == "aiosqlite" or extra == "all"
Requires-Dist: asyncmy (>=0.2.8,<0.3.0) ; extra == "mysql" or extra == "asyncmy" or extra == "all"
Requires-Dist: asyncpg (>=0.28.0,<0.29.0) ; extra == "postgresql" or extra == "asyncpg" or extra == "all"
Requires-Dist: khemia (>=0.1.1,<0.2.0)
Requires-Dist: pydantic (>=2.7.0,<3.0.0)
